lib_parameter/__init__.py
lib_parameter/__init__conf__.py
lib_parameter/lib_parameter.py
lib_parameter/lib_parameter_cli.py
lib_parameter/py.typed
lib_parameter-1.1.15.dist-info/LICENSE
lib_parameter-1.1.15.dist-info/METADATA
lib_parameter-1.1.15.dist-info/WHEEL
lib_parameter-1.1.15.dist-info/entry_points.txt
lib_parameter-1.1.15.dist-info/top_level.txt
lib_parameter-1.1.15.dist-info/RECORD
